{
  "project_info": {
    "project_number": "1061066372559",
    "firebase_url": "https://lubstore-89f45.firebaseio.com",
    "project_id": "lubstore-89f45",
    "storage_bucket": "lubstore-89f45.appspot.com"
  },
  "client": [
    {
      "client_info": {
        "mobilesdk_app_id": "1:1061066372559:android:783d18bf75e60bdf744eba",
        "android_client_info": {
          "package_name": "com.lubsolution.store"
        }
      },
      "oauth_client": [
        {
          "client_id": "1061066372559-rmk2ne03dbjt99lb8uis6cn78j2p1h9u.apps.googleusercontent.com",
          "client_type": 1,
          "android_info": {
            "package_name": "com.lubsolution.store",
            "certificate_hash": "72da1990e3b40d85413dd99254695087d88cc154"
          }
        },
        {
          "client_id": "1061066372559-f0ocbo0vn55cm00crl8f5j6rdoi89mrd.apps.googleusercontent.com",
          "client_type": 3
        }
      ],
      "api_key": [
        {
          "current_key": "AIzaSyAg1NLGVX2j_4MX4LTYhDtx2s9t5AJf69E"
        }
      ],
      "services": {
        "appinvite_service": {
          "other_platform_oauth_client": [
            {
              "client_id": "1061066372559-f0ocbo0vn55cm00crl8f5j6rdoi89mrd.apps.googleusercontent.com",
              "client_type": 3
            }
          ]
        }
      }
    }
  ],
  "configuration_version": "1"
}